outcome/devkit/__init__.py
outcome/devkit/coverage_fn.py
outcome/devkit/env_coverage.py
outcome/devkit/invoke/__init__.py
outcome/devkit/invoke/app.py
outcome/devkit/invoke/docker.py
outcome/devkit/invoke/env.py
outcome/devkit/invoke/tasks/__init__.py
outcome/devkit/invoke/tasks/check.py
outcome/devkit/invoke/tasks/clean.py
outcome/devkit/invoke/tasks/database.py
outcome/devkit/invoke/tasks/docker.py
outcome/devkit/invoke/tasks/gcp.py
outcome/devkit/invoke/tasks/git.py
outcome/devkit/invoke/tasks/pact.py
outcome/devkit/invoke/tasks/release.py
outcome/devkit/invoke/tasks/setup.py
outcome/devkit/invoke/tasks/test.py
outcome/devkit/py.typed
outcome/devkit/test_helpers.py
outcome/devkit/without_modules.py
outcome_devkit-7.2.0.dist-info/WHEEL
outcome_devkit-7.2.0.dist-info/METADATA
outcome_devkit-7.2.0.dist-info/RECORD
