Metadata-Version: 2.1
Name: outcome-devkit
Version: 7.2.0
Summary: A package containing common dev dependencies for python projects.
Home-page: https://github.com/outcome-co/devkit-py
License: ISC
Author: Douglas Willcocks
Author-email: douglas@outcome.co
Requires-Python: >=3.8.6,<4.0.0
Classifier: License :: OSI Approved
Classifier: Programming Language :: Python :: 3
Classifier: Programming Language :: Python :: 3.9
Requires-Dist: black (>=20.8b1,<21.0)
Requires-Dist: colored-traceback (>=0.3.0,<0.4.0)
Requires-Dist: coverage (>=5.0.3,<6.0.0)
Requires-Dist: flake8 (>=3.7.9,<4.0.0)
Requires-Dist: flake8-breakpoint (>=1.1.0,<2.0.0)
Requires-Dist: flake8-builtins (>=1.5.2,<2.0.0)
Requires-Dist: flake8-colors (>=0.1.6,<0.2.0)
Requires-Dist: flake8-commas (>=2.0.0,<3.0.0)
Requires-Dist: flake8-if-expr (>=1.0.0,<2.0.0)
Requires-Dist: flake8-mutable (>=1.2.0,<2.0.0)
Requires-Dist: flake8-print (>=3.1.4,<5.0.0)
Requires-Dist: flake8-pytest (>=1.3,<2.0)
Requires-Dist: flake8-return (>=1.1.1,<2.0.0)
Requires-Dist: ipython (>=7.13.0,<8.0.0)
Requires-Dist: isort (>=5.8.0,<6.0.0)
Requires-Dist: magicinvoke (>=2.4.5,<3.0.0)
Requires-Dist: outcome-read-toml (>=2.1.1,<3.0.0)
Requires-Dist: outcome-stubs (>=0.5.4,<0.6.0)
Requires-Dist: outcome-utils (>=5.0.3,<6.0.0)
Requires-Dist: pactman (>=2.28.0,<3.0.0)
Requires-Dist: pdbpp (>=0.10.2,<0.11.0)
Requires-Dist: poetry (==1.1.5)
Requires-Dist: pre-commit (>=2.10.1,<3.0.0)
Requires-Dist: pydantic (>=1.7.3,<2.0.0)
Requires-Dist: pygit2 (>=1.5.0,<2.0.0)
Requires-Dist: pytest (>=6.2.2,<7.0.0)
Requires-Dist: pytest-asyncio (>=0.12,<0.16)
Requires-Dist: rich (>=9.11.0,<10.0.0)
Requires-Dist: syrupy (>=1.1.0,<2.0.0)
Requires-Dist: wemake-python-styleguide (>=0.15.1,<0.16.0)
Project-URL: Documentation, https://github.com/outcome-co/devkit-py#README
Project-URL: Repository, https://github.com/outcome-co/devkit-py
